{
  "Alavés": {
    "Antonio Sivera": "979797",
    "Aleksandar Sedlar": "897331",
    "Abdel Abqar": "922843",
    "Ander Guevara": "903124",
    "Antonio Blanco": "966402",
    "Nahuel Tenaglia": "930937",
    "Kike Garcia": "2759403",
    "Jon Guridi": "905274",
    "Carlos Benavidez": "897080",
    "Jesus Owono": "896937",
    "Adrian Rodriguez": "896904",
    "Asier Villalibre": "897023",
    "Carles Aleña": "910705",
    "Joan Jordan": "1079223",
    "Manu Sanchez": "897501",
    "Carlos Vicente": "19329294",
    "Santiago Mouriño": "896938",
    "Carlos Martin": "897002",
    "Tomas Conechny": "897392",
    "Moussa Diarra": "897197",
    "Hugo Novoa": "897005",
    "Eneko Ortiz": "896898",
    "Adrian Pica": "896901",
    "Julen Lartitegi": "896897",
    "Toni Martinez": "897985",
    "Pau Cabanes": "896930",
    "Facundo Garces": "899901",
    "Alejandro Jay": "882211",
    "Egoitz Muñoz": "867780",
    "Gregoire Swiderski": "877405",
    "Daouda Doumbia": "874616",
    "Ander Sanchez": "600000",
    "Gaizka Garcia": "400000",
    "Tomas Mendes": "500000",
    "Stoichkov": "891011",
    "Luka Romero": "809559",
    "Abde Rebbach": "791853"
  },
  "Athletic": {
    "Andoni Gorosabel": "941639",
    "Unai Simon": "10995205",
    "Dani Vivian": "48541631",
    "Aitor Paredes": "3093318",
    "Yeray Alvarez": "7151155",
    "Mikel Vesga": "897383",
    "Alex Berenguer": "54387545",
    "Oihan Sancet": "81651222",
    "Iñaki Williams": "59601259",
    "Nico Williams": "94090276",
    "Gorka Guruzeta": "5445234",
    "Julen Agirrezabala": "1552454",
    "Iñigo Lekue": "897007",
    "Iñigo Ruiz De Galarreta": "2938886",
    "Yuri Berchiche": "3446986",
    "Oscar De Marcos": "2948412",
    "Beñat Prados": "947105",
    "Unai Gomez": "897102",
    "Unai Nuñez": "897968",
    "Alvaro Djalo": "897784",
    "Oier Gastesi": "896912",
    "Mikel Jauregizar": "3017526",
    "Adama Boiro": "897392",
    "Peio Canales": "896910",
    "Maroan Sannadi": "928380",
    "Endika Bujan": "871831",
    "Aingeru Olabarrieta": "882978",
    "Javier Marton": "812554",
    "Nico Serrano": "806918",
    "Ander Herrera": "795002",
    "Alex Padilla": "771663"
  },
  "Atlético": {
    "Giménez": "18451556",
    "Cesar Azpilicueta": "900455",
    "Rodrigo De Paul": "37588692",
    "Koke Resurreccion": "2637756",
    "Antoine Griezmann": "63972048",
    "Angel Correa": "944017",
    "Thomas Lemar": "896968",
    "Samuel Lino": "6743547",
    "Jan Oblak": "29596144",
    "Marcos Llorente": "50632464",
    "Nahuel Molina": "2303601",
    "Javi Galan": "1188369",
    "Axel Witsel": "915320",
    "Reinildo Mandava": "903242",
    "Pablo Barrios": "59289134",
    "Rodrigo Riquelme": "900012",
    "Antonio Gomis": "897214",
    "Ilias Kostis": "896902",
    "Robin Le Normand": "15167715",
    "Alexander Sorloth": "20049787",
    "Giuliano Simeone": "27052405",
    "Clement Lenglet": "8014479",
    "Julian Alvarez": "140138661",
    "Conor Gallagher": "4252733",
    "Juan Musso": "897145",
    "Alejandro Iturbe": "896917",
    "Geronimo Spina": "896910",
    "Javi Serrano": "896910",
    "Carlos Gimenez": "891724",
    "Aitor Gismera": "893628",
    "Adrian Niño": "867780",
    "Rayane Belaid": "867780",
    "Martin Pascual": "275441",
    "Selu Diallo": "1000000"
  },
  "Barcelona": {
    "Marc-Andre Ter Stegen": "962590",
    "Alejandro Balde": "35540066",
    "Ronald Araujo": "18389988",
    "Iñigo Martinez": "64948500",
    "Pablo Gavi": "18758631",
    "Ferran Torres": "28278231",
    "Pedri Gonzalez": "139891538",
    "Robert Lewandowski": "104619367",
    "Raphinha": "129712914",
    "Andreas Christensen": "897868",
    "Frenkie De Jong": "45134072",
    "Jules Kounde": "65537679",
    "Lamine Yamal": "148108017",
    "Marc Casado": "13797590",
    "Diego Kochen": "896939",
    "Pau Cubarsi": "52991469",
    "Ander Astralaga": "896910",
    "Fermin Lopez": "6815744",
    "Pablo Torre": "899724",
    "Eric Garcia": "1698795",
    "Iñaki Peña": "2728440",
    "Hector Fort": "903047",
    "Ansu Fati": "923054",
    "Pau Victor": "906076",
    "Dani Olmo": "86982946",
    "Gerard Martin": "1311978",
    "Sergi Dominguez": "896914",
    "Marc Bernal": "897014",
    "Andres Cuenca": "896914",
    "Wojciech Szczesny": "22580927",
    "Aron Yaakobishvili": "896859",
    "Toni Fernandez": "892736",
    "Guille Fernandez": "892736",
    "Noah Darvich": "892736",
    "Alvaro Cortes": "889153",
    "Ivan Cedric": "2000000"
  },
  "Betis": {
    "Hector Bellerin": "899092",
    "Ez Abde": "4423913",
    "Carvalho": "897290",
    "Marc Bartra": "16698544",
    "Marc Roca": "971454",
    "Isco": "89536745",
    "Youssouf Sabaly": "951700",
    "Aitor Ruibal": "897645",
    "Sergi Altimira": "961756",
    "Guilherme Fernandes": "861231",
    "Francisco Vieites": "897884",
    "Chimy Avila": "903639",
    "Johnny Cardoso": "5874363",
    "Cedric Bakambu": "899025",
    "Pablo Fornals": "4061755",
    "Adrian San Miguel": "927358",
    "Diego Javier Llorente": "30070607",
    "Romain Perraud": "936676",
    "Ricardo Rodriguez": "911015",
    "Lucas Alcazar": "896910",
    "Carlos Guirao": "877345",
    "Natan": "2307411",
    "Giovani Lo Celso": "48001852",
    "Manu Gonzalez": "896902",
    "Antony": "67913050",
    "Dani Perez": "885076",
    "Cucho Hernandez": "9830681",
    "Jesus Rodriguez": "3706107",
    "Nobel Mendy": "874042",
    "Pablo Busto": "870908",
    "Angel Ortiz": "867780",
    "Mateo Flores": "867780",
    "Carlos Reina": "867780",
    "Pablo Garcia": "882978",
    "Sergio Arribas Prieto": "864026",
    "Xavi Pleguezuelo": "860682",
    "German Garcia": "866255",
    "Marciano Sanca": "521249",
    "Vitor Roque": "9191397",
    "Iker Losada": "813657",
    "Juanmi Jimenez": "821842",
    "Rui Silva": "11264029",
    "Assane Diao": "775509"
  },
  "Celta": {
    "Marcos Alonso": "14938960",
    "Borja Iglesias": "6201495",
    "Vicente Guaita": "3333162",
    "Mihailo Ristic": "896903",
    "Carl Starfelt": "4750250",
    "Oscar Mingueza": "17308927",
    "Fran Beltran": "925914",
    "Iago Aspas": "16192629",
    "Franco Cervi": "896928",
    "Ivan Villar": "898047",
    "Williot Swedberg": "1051980",
    "Carlos Dominguez": "897161",
    "Hugo Sotelo": "897635",
    "Coke Carrillo": "881123",
    "Jailson": "897136",
    "Ilaix Moriba": "915485",
    "Javier Manquillo": "896922",
    "Sergio Carreira": "942146",
    "Iker Losada": "897122",
    "Pablo Duran": "920817",
    "Cesar Fernandez": "896917",
    "Marc Vidal": "896937",
    "Javi Rodriguez": "960301",
    "Hugo Alvarez": "916445",
    "Damian Rodriguez": "897344",
    "Alfonso Gonzalez": "1487109",
    "Jones El-Abdellaoui": "906944",
    "Yoel Lago": "887920",
    "Miguel Roman": "881004",
    "Fer Lopez": "882019",
    "Hugo Gonzalez": "700000",
    "Ivan Garri": "300000",
    "Anastasios Douvikas": "893210",
    "Joseph Aidoo": "807192",
    "Luca De La Torre": "797513",
    "Jonathan Bamba": "850414",
    "Tadeo Allende": "788431"
  },
  "Espanyol": {
    "Urko Gonzalez De Zarate": "898870",
    "Joan Garcia": "27570733",
    "Sergi Gomez": "897135",
    "Fernando Calero": "897237",
    "Leandro Cabrera": "1738065",
    "Javi Puado": "28253240",
    "Antoniu Roca": "896901",
    "Pol Lozano": "896936",
    "Pere Milla": "897027",
    "Fernando Pacheco": "897036",
    "Brian Olivan": "896966",
    "Jose Gragera": "896947",
    "Jofre Carreras": "1253367",
    "Alvaro Aguado": "897151",
    "Omar Sadik": "896902",
    "Edu Exposito": "960423",
    "Omar El Hilali": "1434723",
    "Rafel Bauza": "896902",
    "Jose Luis Catala": "896901",
    "Llorenç Serred": "918467",
    "Angel Fortuño": "896965",
    "Alvaro Tejero": "903093",
    "Carlos Romero": "1250030",
    "Alex Kral": "960085",
    "Marash Kumbulla": "3775711",
    "Walid Cheddira": "897201",
    "Alejo Veliz": "898342",
    "Roberto Fernandez": "1255625",
    "Pablo Ramon": "892736",
    "Alex Almansa": "878968",
    "Pol Tristan": "867780",
    "Justin Smith": "867780",
    "Angel Gomez": "300000",
    "Irvin Cardona": "813545",
    "Joan Puig": "1000000",
    "Salvi Sanchez": "797702"
  },
  "Getafe": {
    "Alex Sola": "902778",
    "Carles Perez": "904927",
    "Dakonam Djene": "2568861",
    "Luis Milla": "38226099",
    "Domingos Duarte": "999286",
    "Mauro Arambarri": "5836930",
    "David Soria": "6878730",
    "Omar Alderete": "37511951",
    "Diego Rico": "9832229",
    "Borja Mayoral": "1304938",
    "Juan Iglesias": "1429585",
    "Gorka Rivera": "896897",
    "Ramon Terrats": "1415776",
    "Yellu Santiago": "896941",
    "Peter Gonzalez": "897084",
    "Juanmi Jimenez": "898253",
    "Alvaro Rodriguez": "897547",
    "Jiri Letacek": "896984",
    "Christantus Uche": "3283791",
    "Diego Ferrer": "896910",
    "Juan Berrocal": "897223",
    "Bertug Yildirim": "897518",
    "Juan Bernat": "898985",
    "Alberto Risco": "896916",
    "Coba Gomes": "898713",
    "Allan Nyom": "913573",
    "Abdoulaye Keita": "892736",
    "Djordjije Medenica": "892736",
    "David Arguelles": "892021",
    "Martin Cuellar": "866255",
    "Ismael Bekhoucha": "871831",
    "Luca Lohr": "855107",
    "Chrisantus Uche": "4171661",
    "Fabrizio Angileri": "720395",
    "Nabil Aberdin": "820540",
    "Carles Aleña": "813969",
    "John Patrick Finn": "790856"
  },
  "Girona": {
    "Oriol Romeu": "897461",
    "Juan Carlos Martin": "896985",
    "Miguel Gutierrez": "23247516",
    "Arnau Martinez": "1352056",
    "David Lopez": "3014894",
    "Christian Stuani": "897568",
    "Viktor Tsygankov": "3039293",
    "Paulo Gazzaniga": "5408666",
    "Juanpe Ramirez": "897033",
    "Daley Blind": "3596749",
    "Yangel Herrera": "7262079",
    "Jhon Solis": "896907",
    "Ivan Martin": "1154008",
    "Cristian Portu": "897245",
    "Ricard Artero": "937439",
    "Ladislav Krejci": "1003349",
    "Alejandro Frances": "897935",
    "Donny Van De Beek": "1262419",
    "Abel Ruiz": "918128",
    "Bryan Gil": "6555032",
    "Arnaut Danjuma": "1519944",
    "Gabriel Misehouy": "897068",
    "Bojan Miovski": "898675",
    "Yaser Asprilla": "918491",
    "Guillem Trilla": "892736",
    "Raul Martinez": "892736",
    "Lucas Garcia": "888438",
    "Antal Yaakobishvili": "889871",
    "Papa Dame Ba": "888438",
    "Juan Arango": "891305",
    "Dawda Camara": "889871",
    "Enric Garcia": "888795",
    "Aleksandar Andreev": "887722",
    "Ferran Ruiz": "888438",
    "Jastin": "887722",
    "Arthur Melo": "1981424",
    "Vladyslav Krapyvtsov": "891724",
    "Oriol Comas": "866255",
    "Min Su Kim": "611759",
    "Pau Lopez": "829515",
    "Silvi Clua": "300000"
  },
  "Las Palmas": {
    "Jaime Mata": "897044",
    "Marvin Park": "897029",
    "Alex Suarez": "899284",
    "Javi Muñoz": "929812",
    "Sandro Ramirez": "18677872",
    "Alberto Moleiro": "23069011",
    "Enzo Loiodice": "897031",
    "Mika Marmol": "918614",
    "Marc Cardona": "896963",
    "Kirian Rodriguez": "2487449",
    "Juanma Herzog": "896964",
    "Adnan Januzaj": "897490",
    "Benito Ramirez": "896907",
    "Jose Campaña": "899055",
    "Fuster": "897126",
    "Jasper Cillessen": "2774205",
    "Alex Muñoz": "905813",
    "Viti Rozada": "897397",
    "Dinko Horkas": "897109",
    "Oliver Mcburnie": "1039402",
    "Scott Mckenna": "905341",
    "Alvaro Killane": "896901",
    "Valentin Pezzolesi": "896910",
    "Dario Essugo": "902253",
    "Fábio Silva": "16126976",
    "Stefan Bajcetic": "1312813",
    "Andy Pelmard": "930615",
    "Victor Puig": "891724",
    "Valentino Raca": "876932",
    "Sergio Viera": "871831",
    "Israel Mora": "863469",
    "Aboubacar Bassinga": "882978",
    "Elias Romero": "866255",
    "Sergio Ruiz": "860682",
    "Alvaro Valles": "861710",
    "Daley Sinkgraven": "811480",
    "Pejiño": "812017",
    "Ivan Gil": "723622",
    "Fabio": "695736"
  },
  "Leganés": {
    "Juan Cruz": "22170516",
    "Javi Hernandez": "911120",
    "Renato Tapia": "899911",
    "Oscar Rodriguez": "900650",
    "Munir El Haddadi": "897315",
    "Matija Nastasic": "907842",
    "Darko Brasanac": "900606",
    "Marko Dmitrovic": "1319375",
    "Adria Altimira": "897070",
    "Miguel De La Fuente": "897439",
    "Jorge Saenz": "905658",
    "Yvan Neyou": "959519",
    "Diego Garcia": "896965",
    "Julian Chicco": "896910",
    "Sergio Gonzalez": "8692386",
    "Daniel Raba": "5540077",
    "Juan Soriano": "901382",
    "Valentin Rosier": "2340262",
    "Enric Franquesa": "898081",
    "Seydouba Cisse": "2841373",
    "Roberto Lopez": "897569",
    "Alvin Abajas": "896895",
    "Joao Urbaez": "896894",
    "Hugo Solozabal": "876503",
    "Iker Bachiller": "878406",
    "Duk": "1045983",
    "Borna Barisic": "1006245",
    "Fer Rodriguez": "867780",
    "Guillermo Ruiz": "868487",
    "Jackson Porozo": "809156",
    "Sebastien Haller": "1430805"
  },
  "Mallorca": {
    "Robert Navarro": "1038587",
    "Valery Fernandez": "897144",
    "Antonio Lato": "896946",
    "Omar Mascarell": "899460",
    "Jose Manuel Copete": "1019647",
    "Vedat Muriqi": "9560511",
    "Manuel Morlanes": "930833",
    "Abdon Prats": "897071",
    "Sergi Darder": "32081511",
    "Samu Costa": "4241205",
    "Dominik Greif": "1701722",
    "Dani Rodriguez": "27168355",
    "Pablo Maffeo": "8845200",
    "Cyle Larin": "1121370",
    "Antonio Sanchez": "898214",
    "Antonio Raillo": "54869066",
    "Martin Valjent": "14183036",
    "Ivan Cuellar": "896920",
    "Johan Mojica": "22623921",
    "Takuma Asano": "901600",
    "Mateu Morey": "897004",
    "Leo Roman": "897982",
    "Chiquinho": "897433",
    "Jan Salas": "896933",
    "David Lopez": "908846",
    "Sebas Wade": "889821",
    "Marc Domenech": "891724",
    "Pere Joan Garcia": "870908",
    "Daniel Luna": "811154",
    "Siebe Van Der Heyden": "804902",
    "Javi Llabres": "788566"
  },
  "Osasuna": {
    "Bryan Zaragoza": "11694174",
    "Sergio Herrera": "6522093",
    "Juan Cruz": "897031",
    "Unai Garcia": "896921",
    "Lucas Torro": "2911079",
    "Jon Moncayola": "901029",
    "Aimar Oroz": "13798330",
    "Kike Barja": "896924",
    "Jesus Areso": "970045",
    "Aitor Fernandez": "896952",
    "Ruben Garcia": "24587308",
    "Ruben Peña": "897062",
    "Moi Gomez": "897343",
    "Ante Budimir": "57807061",
    "Pablo Ibañez": "897146",
    "Jose Arnaiz": "896924",
    "Alejandro Catena": "12302391",
    "Jorge Herrando": "901228",
    "Iker Muñoz": "897064",
    "Dimitrios Stamatakis": "896901",
    "Pablo Valencia": "878502",
    "Raul Garcia": "897201",
    "Boyomo": "12444973",
    "Abel Bretones": "1199870",
    "Diego Espejo": "867780",
    "Asier Osambela": "867780",
    "Iñigo Arguibide": "869046",
    "Carlos Lumbreras": "866255",
    "Nacho Vidal": "798590",
    "Javi Martinez": "743766",
    "Iker Benito": "694266"
  },
  "Rayo": {
    "Adrian Embarba": "899166",
    "Sergi Guardiola": "898556",
    "Gerard Gumbau": "897039",
    "Andrei Ratiu": "44964942",
    "Pep Chavarria": "1056252",
    "Aridane Hernandez": "922963",
    "Isi Palazon": "9397718",
    "Oscar Trejo": "896984",
    "Randy Nteka": "897122",
    "Pacha Espino": "897161",
    "Dani Cardenas": "897353",
    "Abdul Mumin": "7734618",
    "Unai Lopez": "1069512",
    "Alvaro Garcia": "10101784",
    "Jorge De Frutos": "16676241",
    "Ivan Balliu": "897331",
    "Pathe Ciss": "2201881",
    "Raul De Tomas": "896954",
    "Oscar Valentin": "930692",
    "Florian Lejeune": "22231857",
    "Sergio Camello": "1094475",
    "Augusto Batalla": "4539253",
    "Joni Montiel": "898944",
    "Pedro Diaz": "2410169",
    "Etienne Eto'O": "896912",
    "Pelayo Fernandez": "897037",
    "Marco De La Sias": "896907",
    "Juanpe Gil": "867780",
    "Adrian Molina": "869046",
    "James Rodriguez": "2187248",
    "Diego Mendez": "300000"
  },
  "Real Madrid": {
    "Jesus Vallejo": "897407",
    "Thibaut Courtois": "33072498",
    "Daniel Carvajal": "944094",
    "Eder Militao": "1154387",
    "David Alaba": "1964418",
    "Jude Bellingham": "127971579",
    "Vinicius Junior": "130438899",
    "Luka Modric": "29488454",
    "Rodrygo Goes": "79846581",
    "Eduardo Camavinga": "18240129",
    "Andriy Lunin": "903222",
    "Federico Valverde": "127299983",
    "Lucas Vazquez": "15402377",
    "Aurelien Tchouameni": "34682457",
    "Dani Ceballos": "5760660",
    "Fran Garcia": "10938480",
    "Brahim Diaz": "15671235",
    "Antonio Rudiger": "47585201",
    "Ferland Mendy": "1652105",
    "Arda Guler": "4067920",
    "Kylian Mbappe": "145213581",
    "Endrick": "933184",
    "Jacobo Ramon": "896910",
    "Raul Asencio": "48748851",
    "Sergio Mestre": "889821",
    "David Jimenez": "889821",
    "Gonzalo Garcia": "883429",
    "Daniel Yañez": "883429",
    "Victor Muñoz": "883429",
    "Hugo De Llanos": "883429",
    "Diego Aguado": "883429",
    "Lorenzo Aguado": "883429",
    "Fran Gonzalez": "889964",
    "Chema Andres": "889821",
    "Pol Fortuny": "877405",
    "Mario Rivas": "894129",
    "Diego Piñeiro": "300000"
  },
  "Real Sociedad": {
    "Javi Lopez": "901341",
    "Alex Remiro": "12673699",
    "Alvaro Odriozola": "896946",
    "Aihen Muñoz": "897098",
    "Martin Zubimendi": "37479033",
    "Igor Zubeldia": "5555837",
    "Aritz Elustondo": "921500",
    "Ander Barrenetxea": "915096",
    "Pablo Marin": "920692",
    "Mikel Oyarzabal": "20066096",
    "Arsen Zakharyan": "897011",
    "Takefusa Kubo": "46177012",
    "Jon Ander Olasagasti": "896918",
    "Hamari Traore": "910149",
    "Jon Pacheco": "897925",
    "Beñat Turrientes": "898333",
    "Brais Mendez": "3888130",
    "Unai Marrero": "896910",
    "Aitor Fraga": "896913",
    "Sheraldo Becker": "950609",
    "Sergio Gomez": "40592771",
    "Luka Sucic": "14277692",
    "Jon Martin": "896913",
    "Jon Aramburu": "4701131",
    "Egoitz Arana": "896904",
    "Nayef Aguerd": "13665609",
    "Orri Steinn Oskarsson": "901653",
    "Arkaitz Mariezkurrena": "874042",
    "Mikel Goti": "874042",
    "Iñaki Ruperez": "874042",
    "Jon Balda": "874042",
    "Urko Gonzalez De Zarate": "797460",
    "Umar Sadiq": "729911",
    "Magunacelaya": "677966"
  },
  "Sevilla": {
    "Saul Ñiguez": "1219237",
    "Jose Angel Carmona": "3526324",
    "Adria Pedrosa": "965543",
    "Nemanja Gudelj": "1960681",
    "Suso Fernandez": "896947",
    "Dodi Lukebakio": "104418081",
    "Örjan Nyland": "2383387",
    "Tanguy Nianzou": "897059",
    "Djibril Sow": "2098602",
    "Loic Bade": "37694515",
    "Marcao": "896928",
    "Juanlu Sanchez": "979095",
    "Manu Bueno": "897577",
    "Matias Arbol": "896897",
    "Kike Salas": "1607485",
    "Isaac Romero": "2267711",
    "Lucien Agoume": "1113526",
    "Albert Sambi Lokonga": "905235",
    "Peque": "897685",
    "Chidera Ejuke": "7585394",
    "Alvaro Fernandez": "897711",
    "Stanis Idumbo Muzambo": "896977",
    "Pablo Rivera": "896913",
    "Alberto Collado": "896913",
    "Alberto Flores": "896910",
    "Ruben Vargas": "3997485",
    "Akor Adams": "1218542",
    "Mateo Mejia": "889821",
    "Ramon Martinez": "881004",
    "Isra Dominguez": "888127",
    "Alvaro Garcia Pascual": "877168",
    "Andres Castrin": "877168",
    "Dario Benavides": "877168",
    "Rafael Romero": "877168",
    "Leandro Antonetti": "888553",
    "Diego Hormigo": "866255",
    "Kelechi Iheanacho": "840662",
    "Valentin Barco": "849138",
    "Pedro Ortiz": "805411",
    "Gonzalo Montiel": "829290",
    "Jesus Navas": "1199212"
  },
  "Valencia": {
    "Luis Rioja": "34288934",
    "Stole Dimitrievski": "897646",
    "Umar Sadiq": "1890253",
    "Rafa Mir": "897402",
    "Jaume Domenech": "896921",
    "Christian Mosquera": "6576361",
    "Mouctar Diakhaby": "917018",
    "Hugo Guillamon": "897070",
    "Sergi Canos": "896990",
    "Javi Guerra": "6094234",
    "Hugo Duro": "2507324",
    "Andre Almeida": "1841913",
    "Thierry Correia": "843337",
    "Jose Gaya": "1812551",
    "Diego Lopez": "17859998",
    "Pepelu": "1607912",
    "Dimitri Foulquier": "903888",
    "Jesus Vazquez": "897313",
    "Fran Perez": "897004",
    "Giorgi Mamardashvili": "5889815",
    "Martin Tejon": "896901",
    "Cesar Tarrega": "5086049",
    "Ruben Iranzo": "874402",
    "Yarek Gasiorowski": "897201",
    "Raul Jimenez": "896913",
    "Rodrigo Abajas": "896913",
    "Ali Fadal": "896913",
    "David Otorbi": "896902",
    "Iker Cordoba": "896907",
    "Enzo Barrenechea": "1732467",
    "Max Aarons": "1015569",
    "Warren Madrigal": "889821",
    "Ivan Jaime": "1023199",
    "Ismael Santana": "883429",
    "Pablo Lopez": "882978",
    "Pedro Alemañ": "868487",
    "Vicent Abril": "877405",
    "Mario Dominguez": "500000",
    "Dani Gomez": "819816",
    "Maximiliano Caufriez": "819825"
  },
  "Valladolid": {
    "Darwin Machis": "897079",
    "Joseph Aidoo": "896965",
    "Juan Miguel Latasa": "897276",
    "Andre Ferreira": "896979",
    "Amath Ndiaye": "897433",
    "Cenk Özkacar": "896982",
    "Selim Amallah": "907044",
    "Mamadou Sylla": "898756",
    "Luis Perez": "902822",
    "David Torres": "896922",
    "Javi Sanchez": "897182",
    "Marcos Andre": "896924",
    "Ivan Sanchez": "897345",
    "Stanko Juric": "897244",
    "Anuar Mohamed": "896915",
    "Kenedy": "896917",
    "Raul Moro": "7839091",
    "Adrian Arnu": "983413",
    "Arnau Rafus": "896899",
    "Eray Comert": "897275",
    "Karl Hein": "1446738",
    "Chuki": "896901",
    "Mario Martin": "897001",
    "Raul Chasco": "896902",
    "Koke Iglesias": "896902",
    "Tamas Nikitscher": "930393",
    "Mario Maroto": "889821",
    "Florian Grillitsch": "998791",
    "Antonio Candela": "1010717",
    "Adam Aznou": "889226",
    "Eugene Frimpong": "100000",
    "Lucas Rosa": "824679",
    "Kike Perez": "852850",
    "Abdulai Juma Bah": "611943",
    "Cesar De La Hoz": "790664",
    "Victor Meseguer": "785710"
  },
  "Villarreal": {
    "Ayoze Perez": "71500915",
    "Sergi Cardona": "16331752",
    "Raul Albiol": "901925",
    "Santi Comesaña": "7675969",
    "Gerard Moreno": "3418846",
    "Juan Foyth": "3486186",
    "Dani Parejo": "3819070",
    "Alex Baena": "69928591",
    "Kiko Femenia": "983483",
    "Yeremi Pino": "2941405",
    "Denis Suarez": "896946",
    "Alfonso Pedraza": "897033",
    "Ilias Akhomach": "902975",
    "Eric Bailly": "897511",
    "Diego Conde": "3558314",
    "Willy Kambwala": "920309",
    "Nicolas Pepe": "1114643",
    "Pape Gueye": "4969461",
    "Luiz Junior": "927373",
    "Thierno Barry": "13887629",
    "Logan Costa": "1323455",
    "Iker Alvarez": "896905",
    "Pau Navarro": "896901",
    "Arnau Sola": "896916",
    "Antonio Espigares": "896959",
    "Etta Eyong": "896946",
    "Tajon Buchanan": "1468047",
    "Ruben Gomez": "881004",
    "Jean Ives Valou": "883040",
    "Alassane Diatta": "877168",
    "Thiago Ojeda": "877168",
    "Dani Requena": "877405",
    "Ramon Terrats": "812527",
    "Juan Bernat": "829781"
  }
}