{
  "Galatasaray": {
    "Arda Unyay": 0.2,
    "Metehan Baltaci": 0.0
  },
  "Juventus": {
    "Arkadiusz Milik": 0.0,
    "Daniele Rugani": 0.0,
    "Dusan Vlahovic": 0.0,
    "Kenan Yildiz": 0.0
  },
  "Borussia Dortmund": {
    "Emre Can": 0.2,
    "Filippo Mane": 0.2,
    "Marcel Sabitzer": 0.2
  },
  "Atalanta": {
    "Mitchel Bakker": 0.0,
    "Ademola Lookman": 0.0
  },
  "Benfica": {
    "Alexander Bah": 0.2,
    "Richard Rios Montoya": 0.2,
    "Dodi Lukebakio": 0.0
  },
  "Real Madrid": {
    "Raul Asencio": 0.0,
    "Rodrygo": 0.0,
    "Trent Alexander-Arnold": 0.0,
    "Jude Bellingham": 0.0,
    "Ferland Mendy": 0.0,
    "Eder Militao": 0.0,
    "Antonio Rudiger": 0.0
  },
  "Monaco": {
    "Pape Cabral": 0.0,
    "Eric Dier": 0.0,
    "Wout Faes": 0.0,
    "Lukas Hradecky": 0.0,
    "Christian Mawissa Elebi": 0.0,
    "Takumi Minamino": 0.0,
    "Paul Pogba": 0.0,
    "Mohammed Salisu": 0.0
  },
  "PSG": {
    "Khvicha Kvaratskhelia": 0.0,
    "Quentin Ndjantou": 0.0,
    "Fabian Ruiz": 0.0
  },
  "Qarabag FK": {
    "Shakhrudin Magomedaliyev": 0.2
  },
  "Newcastle United": {
    "Sven Botman": 0.2,
    "Lewis Miley": 0.2,
    "Joelinton": 0.0,
    "Bruno Guimaraes": 0.0,
    "Emil Krafth": 0.0,
    "Valentino Livramento": 0.0,
    "Fabian Schar": 0.0
  },
  "Glimt": {},
  "Inter": {
    "Carlos Augusto": 0.0,
    "Nicolo Barella": 0.0,
    "Hakan Calhanoglu": 0.0,
    "Denzel Dumfries": 0.0
  },
  "Club Brugge": {
    "Lynnt Audoor": 0.2,
    "Dani van den Heuvel": 0.2
  },
  "Atlético": {
    "Alexander Sorloth": 0.2,
    "Antoine Griezmann": 0.0,
    "Giuliano Simeone": 0.0
  },
  "Olympiacos": {
    "Alexandros Paschalakis": 0.2,
    "Lorenzo Pirola": 0.2
  },
  "Bayer Leverkusen": {
    "Christian Kofane": 0.2,
    "Ibrahim Maza": 0.2,
    "Nathan Tella": 0.2,
    "Eliesse Ben Seghir": 0.0,
    "Mark Flekken": 0.0
  }
}