{
  "Atalanta": {
    "Marco Carnesecchi": 0.8,
    "Berat Djimsiti": 0.8,
    "Isak Hien": 0.8,
    "Honest Ahanor": 0.8,
    "Raoul Bellanova": 0.8,
    "Ederson": 0.8,
    "Marten de Roon": 0.8,
    "Davide Zappacosta": 0.8,
    "Lazar Samardzic": 0.8,
    "Ademola Lookman": 0.8,
    "Nikola Krstovic": 0.8
  },
  "Sassuolo": {
    "Arijanet Muric": 0.8,
    "S. Walukiewicz": 0.8,
    "Jay Idzes": 0.8,
    "Fali Cande": 0.8,
    "Josh Doig": 0.8,
    "Kristian Thorstvedt": 0.8,
    "Nemanja Matic": 0.8,
    "Ismael Kone": 0.8,
    "Domenico Berardi": 0.8,
    "Andrea Pinamonti": 0.8,
    "Armand Lauriente": 0.8
  },
  "Bologna": {
    "Lukasz Skorupski": 0.8,
    "Nadir Zortea": 0.8,
    "Martin Vitik": 0.8,
    "Jhon Lucumi": 0.8,
    "Juan Miranda": 0.8,
    "Nikola Moro": 0.8,
    "Tommaso Pobega": 0.8,
    "Riccardo Orsolini": 0.8,
    "Jens Odgaard": 0.8,
    "Nicolo Cambiaghi": 0.8,
    "Santiago Castro": 0.8
  },
  "Napoli": {
    "V. Milinkovic-Savic": 0.8,
    "Giovanni Di Lorenzo": 0.8,
    "Amir Rrahmani": 0.8,
    "A. Buongiorno": 0.8,
    "Miguel Gutierrez": 0.8,
    "A. Zambo Anguissa": 0.8,
    "Stanislav Lobotka": 0.8,
    "Scott McTominay": 0.8,
    "Matteo Politano": 0.8,
    "Rasmus Hoejlund": 0.8,
    "Eljif Elmas": 0.8
  },
  "Genoa": {
    "Nicola Leali": 0.8,
    "A. Marcandalli": 0.8,
    "Leo Oestigard": 0.8,
    "Johan Vasquez": 0.8,
    "Brooke Norton-Cuffy": 0.8,
    "Patrizio Masini": 0.8,
    "Morten Frendrup": 0.8,
    "Morten Thorsby": 0.8,
    "Aaron Martin Caricol": 0.8,
    "Vitinha": 0.8,
    "Lorenzo Colombo": 0.8
  },
  "Fiorentina": {
    "David de Gea": 0.8,
    "Marin Pongracic": 0.8,
    "Pablo Mari": 0.8,
    "Luca Ranieri": 0.8,
    "Dodo": 0.8,
    "Rolando Mandragora": 0.8,
    "H. N. Caviglia": 0.8,
    "Nicolo Fagioli": 0.8,
    "Niccolo Fortini": 0.8,
    "Albert Gudmundsson": 0.8,
    "Roberto Piccoli": 0.8
  },
  "Roma": {
    "Mile Svilar": 0.8,
    "Gianluca Mancini": 0.8,
    "Evan N'Dicka": 0.8,
    "Mario Hermoso": 0.8,
    "Mehmet Zeki Celik": 0.8,
    "Manu Kone": 0.8,
    "Bryan Cristante": 0.8,
    "Wesley": 0.8,
    "Matias Soule": 0.8,
    "Lorenzo Pellegrini": 0.8,
    "Artem Dovbyk": 0.8
  },
  "Udinese": {
    "Maduka Okoye": 0.8,
    "Nicolo Bertola": 0.8,
    "Christian Kabasele": 0.8,
    "Oumar Solet": 0.8,
    "Alessandro Zanoli": 0.8,
    "Jurgen Ekkelenkamp": 0.8,
    "Jesper Karlstroem": 0.8,
    "Arthur Atta": 0.8,
    "Hassane Kamara": 0.8,
    "Nicolo Zaniolo": 0.8,
    "Adam Buksa": 0.8
  },
  "Inter": {
    "Yann Sommer": 0.8,
    "Manuel Akanji": 0.8,
    "Yann Aurel Bisseck": 0.8,
    "Alessandro Bastoni": 0.8,
    "Denzel Dumfries": 0.8,
    "Nicolo Barella": 0.8,
    "Hakan Calhanoglu": 0.8,
    "Petar Sucic": 0.8,
    "Federico Dimarco": 0.8,
    "Ange-Yoan Bonny": 0.8,
    "Lautaro Martinez": 0.8
  },
  "Lazio": {
    "Ivan Provedel": 0.8,
    "Manuel Lazzari": 0.8,
    "Mario Gila": 0.8,
    "Oliver Provstgaard": 0.8,
    "Adam Marusic": 0.8,
    "Matteo Guendouzi": 0.8,
    "Danilo Cataldi": 0.8,
    "Toma Basic": 0.8,
    "Gustav Isaksen": 0.8,
    "Boulaye Dia": 0.8,
    "Mattia Zaccagni": 0.8
  }
}