{
  "Celta de Vigo": [
    "Borja Iglesias",
    "Iago Aspas",
    "Borja Iglesias",
    "Bryan Zaragoza",
    "Marcos Alonso",
    "Borja Iglesias"
  ],
  "Real Sociedad": [
    "Mikel Oyarzabal",
    "Mikel Oyarzabal",
    "Brais Méndez",
    "Mikel Oyarzabal",
    "Mikel Oyarzabal",
    "Mikel Oyarzabal"
  ],
  "Real Madrid": [
    "Vinicius Junior",
    "Vinicius Junior",
    "Vinicius Junior",
    "Vinicius Junior",
    "Vinicius Junior",
    "Kylian Mbappé"
  ],
  "Betis": [
    "Isco",
    "Cucho Hernández",
    "Chimy Ávila",
    "Cucho Hernández",
    "Cucho Hernández",
    "Isco"
  ],
  "Villarreal CF": [
    "Ayoze Pérez",
    "Gerard Moreno",
    "Nicolas Pépé",
    "Pape Gueye",
    "Gerard Moreno",
    "Gerard Moreno"
  ],
  "FC Barcelona": [
    "Lamine Yamal",
    "Lamine Yamal",
    "Raphinha",
    "Raphinha",
    "Lamine Yamal",
    "Raphinha"
  ],
  "Athletic": [
    "Gorka Guruzeta",
    "Oihan Sancet",
    "Mikel Jauregizar",
    "Unai Gómez",
    "Oihan Sancet",
    "Nico Williams"
  ],
  "Atlético de Madrid": [
    "Ademola Lookman",
    "Julián Alvarez",
    "Julián Alvarez",
    "Julián Alvarez",
    "Julián Alvarez",
    "Julián Alvarez"
  ],
  "Girona": [
    "Azzedine Ounahi",
    "Cristhian Stuani",
    "Vladyslav Vanat",
    "Vladyslav Vanat",
    "Vladyslav Vanat",
    "Yáser Asprilla"
  ],
  "Rayo Vallecano": [
    "Randy Nteka",
    "Isi Palazón",
    "Jorge de Frutos",
    "Isi Palazón",
    "Isi Palazón",
    "Andrei Rațiu"
  ],
  "Espanyol": [
    "Kike García",
    "Roberto Fernández",
    "Kike García",
    "Javi Puado",
    "Kike García",
    "Javi Puado"
  ],
  "Sevilla FC": [
    "Akor Adams",
    "Akor Adams",
    "Akor Adams",
    "Isaac Romero",
    "Rubén Vargas",
    "Alexis Sánchez"
  ],
  "Levante": [
    "Adrián Dela",
    "Iván Romero",
    "Adrián Dela",
    "Adrián Dela",
    "Karl Etta Eyong",
    "José Luis Morales"
  ],
  "Getafe CF": [
    "Mauro Arambarri",
    "Mauro Arambarri",
    "Mauro Arambarri",
    "Borja Mayoral",
    "Borja Mayoral",
    "Juanmi"
  ],
  "Valencia CF": [
    "Hugo Duro",
    "Hugo Duro",
    "Largie Ramazani",
    "Largie Ramazani",
    "Pepelu",
    "Largie Ramazani"
  ],
  "CA Osasuna": [
    "Ante Budimir",
    "Ante Budimir",
    "Ante Budimir",
    "Ante Budimir",
    "Ante Budimir",
    "Raúl García"
  ],
  "Elche CF": [
    "André Silva",
    "André Silva",
    "Rafa Mir",
    "André Silva",
    "Rafa Mir",
    "Agustín Álvarez"
  ],
  "RCD Mallorca": [
    "Vedat Muriqi",
    "Vedat Muriqi",
    "Vedat Muriqi",
    "Vedat Muriqi",
    "Vedat Muriqi",
    "Abdón Prats"
  ],
  "Alavés": [
    "Toni Martínez",
    "Lucas Boyé",
    "Lucas Boyé",
    "Toni Martínez",
    "Toni Martínez",
    "Carlos Vicente"
  ],
  "Real Oviedo": [
    "Federico Viñas",
    "Josip Brekalo",
    "Federico Viñas",
    "Salomón Rondón",
    "Santi Cazorla",
    "Santiago Colombatto"
  ]
}